{
  "parent": "item/handheld",
  "textures": {
    "layer0": "snweaponry:items/iron_spear"
  },
  "display": {
    "thirdperson_righthand": {
      "rotation": [0, 90, 40],
      "translation": [0, 5, 1.75],
      "scale": [1.25, 1.25, 1.26]
    },
    "thirdperson_lefthand": {
      "rotation": [0, 90, -40],
      "translation": [0, 5, 1.75],
      "scale": [1.25, 1.25, 1.25]
    },
    "firstperson_righthand": {
      "rotation": [0, 90, 40],
      "translation": [0, 5, 2],
      "scale": [1.25, 1.25, 1.25]
    },
    "firstperson_lefthand": {
      "rotation": [0, 90, -40],
      "translation": [0, 5, 2],
      "scale": [1.25, 1.25, 1.25]
    },
    "ground": {
      "translation": [0, 4, 0]
    }
  }
}